NaHDB/NaHDB.cp312-win_amd64.pyd
NaHDB/__init__.py
nahdb-0.1.0.dist-info/METADATA
nahdb-0.1.0.dist-info/WHEEL
nahdb-0.1.0.dist-info/top_level.txt
nahdb-0.1.0.dist-info/RECORD
