Metadata-Version: 2.4
Name: NaHDB
Version: 0.1.0
Summary: NaHDB adalah solusi key-value database modern yang ringan, cepat, dan aman dengan dukungan enkripsi AES-256.
Author-email: Ilman Hendrawan Saputra <hendrawanilman@gmail.com>
License: MIT License
Requires-Python: <4.0,>=3.10
Requires-Dist: pycryptodome>=3.20.0
